<ParameterList>
  <ParameterList name="NOX Solver">
    <Parameter name="Nonlinear Solver" type="string" value="Line Search Based"/>
    <ParameterList name="Line Search">
      <Parameter name="Method" type="string" value="More'-Thuente"/>
    </ParameterList>
    <ParameterList name="Status Test">
      <Parameter name="Max Iterations" type="int" value="20"/>
      <Parameter name="Tolerance" type="double" value="1e-8"/>
    </ParameterList>
    <ParameterList name="Printing">
      <ParameterList name="Output Information">
        <Parameter name="Error" type="bool" value="true"/>
        <Parameter name="Warning" type="bool" value="true"/>
        <Parameter name="Outer Iteration" type="bool" value="true"/>
        <Parameter name="Inner Iteration" type="bool" value="true"/>
        <Parameter name="Parameters" type="bool" value="false"/>
        <Parameter name="Details" type="bool" value="false"/>
        <Parameter name="Linear Solver Details" type="bool" value="false"/>
        <Parameter name="Outer Iteration StatusTest" type="bool" value="false"/>
        <Parameter name="Test Details" type="bool" value="false"/>
        <Parameter name="Stepper Iteration" type="bool" value="false"/>
        <Parameter name="Stepper Details" type="bool" value="false"/>
        <Parameter name="Stepper Parameters" type="bool" value="false"/>
        <Parameter name="Debug" type="bool" value="false"/>
      </ParameterList>
    </ParameterList>
    <ParameterList name="Linear Solver">
      <Parameter name="Max Iterations" type="int" value="500"/>
      <Parameter name="Method" type="string" value="GMRES"/>
      <ParameterList name="Preconditioner">
       <Parameter name="Type" type="string" value="Ifpack"/>
       <Parameter name="Prec Type" type="string" value="ILU"/>
       <Parameter name="Overlap" type="int" value="2"/>
       <ParameterList name="Ifpack Settings">
          <Parameter name="fact: level-of-fill" type="int" value="2"/>
       </ParameterList>
      </ParameterList> 
      <Parameter name="Tolerance" type="double" value="1e-12"/>
      <Parameter name="Type" type="string" value="Aztec"/>
      <Parameter name="Verbosity" type="int" value="0"/>
    </ParameterList>
  </ParameterList>
</ParameterList>
